safetensors_dataset/__init__.py
safetensors_dataset/dict_dataset.py
safetensors_dataset/dict_dataset.pyi
safetensors_dataset/loading.py
safetensors_dataset/protocol.py
safetensors_dataset/safetensors_dict.py
safetensors_dataset/sequence_dataset.py
safetensors_dataset/utils.py
safetensors_dataset/version.py
safetensors_dataset-0.0.11.dist-info/licenses/LICENSE
safetensors_dataset-0.0.11.dist-info/METADATA
safetensors_dataset-0.0.11.dist-info/WHEEL
safetensors_dataset-0.0.11.dist-info/top_level.txt
safetensors_dataset-0.0.11.dist-info/RECORD
